LICENSE
MANIFEST.in
README.md
VERSION
requirements.txt
setup.py
fasta_splitter.egg-info/PKG-INFO
fasta_splitter.egg-info/SOURCES.txt
fasta_splitter.egg-info/dependency_links.txt
fasta_splitter.egg-info/entry_points.txt
fasta_splitter.egg-info/requires.txt
fasta_splitter.egg-info/top_level.txt
fastasplitter_cli/__init__.py
fastasplitter_cli/main.py
fastasplitter_splitter/__init__.py
fastasplitter_splitter/splitter.py
fastasplitter_splitter/splitter_exceptions.py
fastasplitter_splitter/tests/__init__.py
fastasplitter_splitter/tests/test_splitter.py