Metadata-Version: 2.1
Name: fasta-splitter
Version: 0.9.1
Summary: Command line tool to split one multiple sequences fasta file into individual sequences fasta files.
Home-page: https://github.com/alan-lira/fasta-splitter
Author: Alan Lira
Author-email: 
License: MIT
Platform: Operating System :: MacOS
Platform: Operating System :: Microsoft :: Windows :: Windows 10
Platform: Operating System :: POSIX :: Linux
Classifier: Development Status :: 2 - Pre-Alpha
Classifier: Intended Audience :: Developers
Classifier: Intended Audience :: End Users/Desktop
Classifier: Intended Audience :: Science/Research
Classifier: License :: OSI Approved :: MIT License
Classifier: Natural Language :: English
Classifier: Operating System :: MacOS
Classifier: Operating System :: Microsoft :: Windows :: Windows 10
Classifier: Operating System :: POSIX :: Linux
Classifier: Programming Language :: Python :: 3.6
Classifier: Programming Language :: Python :: 3.7
Classifier: Programming Language :: Python :: 3.8
Classifier: Programming Language :: Python :: 3.9
Classifier: Topic :: Scientific/Engineering :: Bio-Informatics
License-File: LICENSE
